{"type":"FeatureCollection", "features": [
{"type":"Feature","geometry":{"type":"Point","coordinates":[2.28786,48.86263]},"properties":{"ID":"FAN_0","name":"Trocadéro"}},
{"type":"Feature","geometry":{"type":"Point","coordinates":[2.35165,48.85667]},"properties":{"ID":"FAN_1","name":"Hotel de Ville"}},
{"type":"Feature","geometry":{"type":"Point","coordinates":[2.3737,48.88441]},"properties":{"ID":"FAN_2","name":"La Villette"}},
{"type":"Feature","geometry":{"type":"Point","coordinates":[2.40376,48.9376]},"properties":{"ID":"FAN_3","name":"Parc Georges Valbon"}}
]}